README.md
setup.py
novamud/__init__.py
novamud/dungeon.py
novamud/player.py
novamud/room.py
novamud/thing.py
novamud.egg-info/PKG-INFO
novamud.egg-info/SOURCES.txt
novamud.egg-info/dependency_links.txt
novamud.egg-info/requires.txt
novamud.egg-info/top_level.txt