Metadata-Version: 2.1
Name: novamud
Version: 0.0.6
Summary: Simple and flexible mud framework for people with only basic knowledge of python
Home-page: https://gitlab.com/hershaw/novamud
Author: Sam Hopkins
Author-email: sam@daredata.engineering
License: UNKNOWN
Platform: UNKNOWN
Classifier: Programming Language :: Python :: 3
Classifier: License :: OSI Approved :: MIT License
